preprocess.py
CTPreprocessing-3.0.0.dist-info/METADATA
CTPreprocessing-3.0.0.dist-info/WHEEL
CTPreprocessing-3.0.0.dist-info/top_level.txt
CTPreprocessing-3.0.0.dist-info/RECORD
