Metadata-Version: 2.1
Name: CTPreprocessing
Version: 3.0.0
Summary: First preprocessing on input dicoms
Author: AIMedic
Author-email: aimedic@gmail.com
License: MIT
Requires-Python: >=3.7
Requires-Dist: numpy
Requires-Dist: scipy
Requires-Dist: scikit-image
Requires-Dist: pydicom
Requires-Dist: simpleitk
Requires-Dist: matplotlib
Requires-Dist: opencv-python (>=4.5)
Provides-Extra: interactive
Requires-Dist: matplotlib (>=2.2.0) ; extra == 'interactive'
Requires-Dist: jupyter ; extra == 'interactive'
